LICENSE
README.md
setup.cfg
setup.py
EESConnect/EES_connect.py
EESConnect/EES_connect_plus.py
EESConnect/__init__.py
EESConnect/constants.py
EES_connector.egg-info/PKG-INFO
EES_connector.egg-info/SOURCES.txt
EES_connector.egg-info/dependency_links.txt
EES_connector.egg-info/requires.txt
EES_connector.egg-info/top_level.txt