Metadata-Version: 2.1
Name: EES-connector
Version: 1.0.0
Summary: Tools for launching EES calculation and retrieving results from python
Home-page: https://www.dief.unifi.it/vp-177-serg-group-english-version.html
Download-URL: https://github.com/SERGGroup/EESConnector/archive/refs/tags/0.2.5.tar.gz
Author: Pietro Ungar
Author-email: pietro.ungar@unifi.it
License: GNU GPLv3
Project-URL: Source, https://github.com/SERGGroup/EESConnector
Project-URL: Tracker, https://github.com/SERGGroup/EESConnector/issues
Platform: UNKNOWN
Classifier: Development Status :: 4 - Beta
Classifier: Intended Audience :: Science/Research
Classifier: Topic :: Scientific/Engineering
Classifier: License :: OSI Approved :: GNU General Public License v3 (GPLv3)
License-File: LICENSE
